{
    "architecture": [
        7,
        100,
        1
    ],
    "batch_size": 1,
    "date_from": "2016-12-02",
    "date_to": "2016-10-04",
    "dates": [
        "2016-10-18",
        "2016-10-17",
        "2016-10-14",
        "2016-10-13",
        "2016-10-12",
        "2016-10-11",
        "2016-10-07",
        "2016-10-06",
        "2016-10-05",
        "2016-10-04"
    ],
    "dropout": null,
    "early_stopping_patience": 5,
    "epochs": 500,
    "features": [
        "Article Sentiment",
        "Impact Score",
        "BULL_MINUS_BEAR",
        "Rolling Std",
        "Rolling Mean",
        "Volume",
        "Adj Close"
    ],
    "history": [
        5.070000310683275,
        5.090000078606612,
        5.010000258278867,
        4.90000003743172,
        5.0,
        5.0600000524044075,
        5.150000131011019,
        5.139999872732153,
        5.309999771666509,
        5.290000003743172
    ],
    "prediction": [
        4.679281655350434,
        4.684670232162756,
        4.7274750882546375,
        4.745892523800023,
        4.692156295397658,
        4.6842080440017355,
        4.762870803295938,
        4.779205163630892,
        4.787786011092516,
        4.758214110186256
    ],
    "symbol": "GRPN",
    "test_accuracy": 92.753876594667872,
    "test_ape_max": 10.052663387157414,
    "test_mae": 0.3718240589384888,
    "test_mape": 7.2461234053321304,
    "test_rmse": 0.38627137045766513,
    "test_set": 10,
    "timesteps": 3,
    "train_accuracy": 96.127172671946369,
    "train_ape_max": 23.46281955905436,
    "train_duration": 8.203059911727905,
    "train_mae": 0.17867772007205529,
    "train_mape": 3.8728273280536345,
    "train_rmse": 0.3253377978954082,
    "train_set": 22,
    "val_set": 5
}