{
    "architecture": [
        7,
        300,
        1
    ],
    "batch_size": 1,
    "date_from": "2016-12-02",
    "date_to": "2016-10-04",
    "dates": [
        "2016-10-18",
        "2016-10-17",
        "2016-10-14",
        "2016-10-13",
        "2016-10-12",
        "2016-10-11",
        "2016-10-07",
        "2016-10-06",
        "2016-10-05",
        "2016-10-04"
    ],
    "dropout": null,
    "early_stopping_patience": 5,
    "epochs": 500,
    "features": [
        "Article Sentiment",
        "Impact Score",
        "BULL_MINUS_BEAR",
        "Rolling Std",
        "Rolling Mean",
        "Volume",
        "Adj Close"
    ],
    "history": [
        5.070000310683275,
        5.090000078606612,
        5.010000258278867,
        4.90000003743172,
        5.0,
        5.0600000524044075,
        5.150000131011019,
        5.139999872732153,
        5.309999771666509,
        5.290000003743172
    ],
    "prediction": [
        3.675400781424584,
        3.8075329569917025,
        3.891386776440176,
        3.9310716752865678,
        3.8774173755610546,
        3.8728883480109344,
        3.8277722001915757,
        3.780797111281883,
        3.7441191127274025,
        3.7503469262451943
    ],
    "symbol": "GRPN",
    "test_accuracy": 74.857105656405679,
    "test_ape_max": 29.489279214180925,
    "test_mae": 1.286126725239666,
    "test_mape": 25.142894343594328,
    "test_rmse": 1.298745806153546,
    "test_set": 10,
    "timesteps": 5,
    "train_accuracy": 96.963659922909343,
    "train_ape_max": 20.572102703238926,
    "train_duration": 9.663486957550049,
    "train_mae": 0.13397755285785148,
    "train_mape": 3.0363400770906588,
    "train_rmse": 0.2792583633872214,
    "train_set": 18,
    "val_set": 7
}