{
    "architecture": [
        7,
        200,
        1
    ],
    "batch_size": 1,
    "date_from": "2016-12-02",
    "date_to": "2016-10-04",
    "dates": [
        "2016-10-18",
        "2016-10-17",
        "2016-10-14",
        "2016-10-13",
        "2016-10-12",
        "2016-10-11",
        "2016-10-07",
        "2016-10-06",
        "2016-10-05",
        "2016-10-04"
    ],
    "dropout": null,
    "early_stopping_patience": 5,
    "epochs": 500,
    "features": [
        "Article Sentiment",
        "Impact Score",
        "BULL_MINUS_BEAR",
        "Rolling Std",
        "Rolling Mean",
        "Volume",
        "Adj Close"
    ],
    "history": [
        5.070000310683275,
        5.090000078606612,
        5.010000258278867,
        4.90000003743172,
        5.0,
        5.0600000524044075,
        5.150000131011019,
        5.139999872732153,
        5.309999771666509,
        5.290000003743172
    ],
    "prediction": [
        4.350821916346844,
        4.362425702715035,
        4.4134741464725655,
        4.444979021392602,
        4.443952877582181,
        4.438698399906271,
        4.465279178867847,
        4.4400102413185545,
        4.405040546038957,
        4.3979274898925
    ],
    "symbol": "GRPN",
    "test_accuracy": 86.610839873032987,
    "test_ape_max": 17.042547354828539,
    "test_mae": 0.68573909960243784,
    "test_mape": 13.389160126967017,
    "test_rmse": 0.6984444533813041,
    "test_set": 10,
    "timesteps": 3,
    "train_accuracy": 95.931811309286729,
    "train_ape_max": 19.293250926150353,
    "train_duration": 8.257516145706177,
    "train_mae": 0.18865698468576461,
    "train_mape": 4.0681886907132689,
    "train_rmse": 0.326139524277267,
    "train_set": 22,
    "val_set": 7
}